[
    {
        "title": "Roman Polanski",
        "year": 1981,
        "result": {
            "id": 588063,
            "original_title": "The South Bank Show: Roman Polanski",
            "title": "The South Bank Show: Roman Polanski",
            "release_date": "1980-05-25",
            "backdrop_path": null,
            "poster_path": "/t3FCanLbMlI8KvhQRc5hPbdRtXO.jpg",
            "overview": "A documentary first presented on the South Bank Show in 1980 about the career of film director Roman Polanski.",
            "vote_average": 0.0,
            "vote_count": 0,
            "result_type": "movie"
        }
    },
    {
        "title": "Karl Hess: Toward Liberty",
        "year": 1981,
        "result": {
            "id": 244373,
            "original_title": "Karl Hess: Toward Liberty",
            "title": "Karl Hess: Toward Liberty",
            "release_date": "1980-10-01",
            "backdrop_path": null,
            "poster_path": "/i0gEpRrcI6tDTRyuTBxpL2oScQf.jpg",
            "overview": "A look at Karl Hess, libertarian intellectual and activist, from his background as a magazine editor in his youth to his work as a Republican speechwriter, as he became simultaneously a writer for Barry Goldwater and a member of Students for a Democratic Society. In the late 1960s he embarked on a new period in his life, moving to rural West Virginia and becoming involved in movements promoting alternative technologies and renewable energy. He discusses his views opposing large institutions, ranging from government to corporations to universities.",
            "vote_average": 6.4,
            "vote_count": 7,
            "result_type": "movie"
        }
    },
    {
        "title": "Hungary",
        "year": 1981,
        "result": {
            "id": 379534,
            "original_title": "Vizsg\u00e1lat Martinovics Ign\u00e1c sz\u00e1szv\u00e1ri ap\u00e1t \u00e9s t\u00e1rsai \u00fcgy\u00e9ben",
            "title": "The Trial of Martinovics and the Hungarian Jacobins",
            "release_date": "1980-01-25",
            "backdrop_path": null,
            "poster_path": "/jIDA1ngddHQ7CGXcXdUN8Of1uU0.jpg",
            "overview": "For this austere, clear and sharp telefeature, Judit Elek focused on the last months of Martinovics\u2019 life: his interrogation by the Austrians, the examining Magistrate Schilling in particular, shown as a battle of wits as well as delusions \u2013 on both sides. Elek had wanted to make this film in the early 1970s, but wasn\u2019t allowed to. When she finally got the chance, the reactions were predictable, as the parallels with recent Hungarian history were simply too obvious for officialdom not to feel anxious. History may not repeat itself, but the variations look eerily similar...",
            "vote_average": 0.0,
            "vote_count": 0,
            "result_type": "movie"
        }
    },
    {
        "title": "Japan",
        "year": 1981,
        "result": {
            "id": 943455,
            "original_title": "In Search of the Japanese",
            "title": "In Search of the Japanese",
            "release_date": "1980-01-01",
            "backdrop_path": null,
            "poster_path": null,
            "overview": "A fictional comedy about Australian and Japanese culture clash.",
            "vote_average": 0.0,
            "vote_count": 0,
            "result_type": "movie"
        }
    },
    {
        "title": "France",
        "year": 1981,
        "result": {
            "id": 259023,
            "original_title": "France/Tour/Detour/Deux/Enfants",
            "title": "France/Tour/Detour/Deux/Enfants",
            "release_date": "1979-01-01",
            "backdrop_path": "/uBOtHJ1ofizqE8yWjPa2whbpc0w.jpg",
            "poster_path": "/fbdo44yEgD9DEbMfwI0w3t3MBhz.jpg",
            "overview": "In this astonishing twelve-part project for and about television \u2014 the title of which refers to a 19th-century French primer Le tour de la France par deux enfants \u2014 Godard and Mi\u00e9ville take a detour through the everyday lives of two children in contemporary France.",
            "vote_average": 6.1,
            "vote_count": 4,
            "result_type": "movie"
        }
    },
    {
        "title": "John Williams",
        "year": 1981,
        "result": {
            "id": 219566,
            "original_title": "Star Wars: Music by John Williams",
            "title": "Star Wars: Music by John Williams",
            "release_date": "1980-05-18",
            "backdrop_path": null,
            "poster_path": "/1meQ6cRrHK7eETjmD3uAdy5qTKY.jpg",
            "overview": "Document\u00e1rio da BBC. Testemunhe John Williams compondo a lend\u00e1ria trilha sonora de O Imp\u00e9rio Contra-Ataca e regendo a Orquestra Sinf\u00f4nica de Londres.",
            "vote_average": 7.3,
            "vote_count": 6,
            "result_type": "movie"
        }
    }
]
